kplr/__init__.py
kplr/api.py
kplr/config.py
kplr/huber.py
kplr/kplr.py
kplr/kplr_version.py
kplr/ld.py
kplr/mast.py
kplr-0.2.3.dist-info/LICENSE.rst
kplr-0.2.3.dist-info/METADATA
kplr-0.2.3.dist-info/WHEEL
kplr-0.2.3.dist-info/top_level.txt
kplr-0.2.3.dist-info/RECORD
