Metadata-Version: 2.1
Name: kplr
Version: 0.2.3
Summary: Tools for working with Kepler data in Python
Home-page: https://github.com/dfm/kplr
Author: Daniel Foreman-Mackey
Author-email: danfm@nyu.edu
License: MIT
Platform: UNKNOWN
Classifier: Intended Audience :: Developers
Classifier: Intended Audience :: Science/Research
Classifier: License :: OSI Approved :: MIT License
Classifier: Operating System :: OS Independent
Classifier: Programming Language :: Python
Classifier: Programming Language :: Python :: 3
Requires-Dist: six
